[{"name":"products","data":[{"user_name":"rudra","total_count":330,"data":[{"createdAt":1638622367144,"path":"/process-matched/Processed-product--1638622367138.csv","name":"Rudra","sheet":"03","business":[],"brand":[],"product_count":69},{"createdAt":1638624022140,"path":"/process-matched/Processed-product--1638624022133.csv","name":"Rudra","sheet":"04","business":[],"brand":[],"product_count":60},{"createdAt":1638710518280,"path":"/process-matched/Processed-product--1638710518275.csv","name":"Rudra","sheet":"05","business":[],"brand":[],"product_count":79},{"createdAt":1638793337030,"path":"/process-matched/Processed-product--1638793337024.csv","name":"Rudra","sheet":"06","product_count":100,"business":[{"name":"bdfoodslimited","count":100}],"brand":[{"name":"bd-food","count":100}]},{"createdAt":1638793712166,"path":"/process-matched/Processed-product--1638793712160.csv","name":"Rudra","sheet":"07","product_count":22,"business":[{"name":"exceltechnologiesltd","count":22}],"brand":[{"name":"samsung","count":22}]}]},{"user_name":"robin","total_count":431,"data":[{"createdAt":1638624730589,"path":"/process-matched/Processed-product--1638624730582.csv","name":"Robin","sheet":"01","business":[],"brand":[],"product_count":155},{"createdAt":1638705451942,"path":"/process-matched/Processed-product--1638705451934.csv","name":"Robin","sheet":"02","business":[],"brand":[],"product_count":218},{"createdAt":1638785843605,"path":"/process-matched/Processed-product--1638785843599.csv","name":"Robin","sheet":"03","product_count":58,"business":[{"name":"orientelectricbd","count":58}],"brand":[{"name":"bonobos","count":58}]}]},{"user_name":"sojib","total_count":473,"data":[{"createdAt":1638626825656,"path":"/process-matched/Processed-product--1638626825648.csv","name":"sojib","sheet":"01","business":[],"brand":[],"product_count":138},{"createdAt":1638629253204,"path":"/process-matched/Processed-product--1638629253199.csv","name":"sojib","sheet":"02","business":[],"brand":[],"product_count":44},{"createdAt":1638715496851,"path":"/process-matched/Processed-product--1638715496844.csv","name":"sojib","sheet":"03","business":[],"brand":[],"product_count":90},{"createdAt":1638772150378,"path":"/process-matched/Processed-product--1638772150373.csv","name":"Sojib","sheet":"04","product_count":27,"business":[{"name":"dreamelectronicsbd","count":27}],"brand":[{"name":"samsung","count":27}]},{"createdAt":1638793869359,"path":"/process-matched/Processed-product--1638793869352.csv","name":"sojib","sheet":"05","product_count":86,"business":[{"name":"daburbangladesh","count":86}],"brand":[{"name":"dabur-amla","count":86}]}]},{"user_name":"shanzida","total_count":338,"data":[{"createdAt":1638628700968,"path":"/process-matched/Processed-product--1638628700960.csv","name":"Shanzida","sheet":"15","business":[],"brand":[],"product_count":97},{"createdAt":1638712339944,"path":"/process-matched/Processed-product--1638712339936.csv","name":"Shanzida","sheet":"16","business":[],"brand":[],"product_count":141},{"createdAt":1638800719361,"path":"/process-matched/Processed-product--1638800719356.csv","name":"Shanzida","sheet":"17","product_count":100,"business":[{"name":"pentagoninternationallimited","count":100}],"brand":[{"name":"kodomo","count":35},{"name":"zact","count":2},{"name":"salz","count":4},{"name":"systema","count":3},{"name":"shokubutsu","count":1},{"name":"un-categorized","count":1},{"name":"lion","count":54}]}]},{"user_name":"shusmita","total_count":540,"data":[{"createdAt":1638680769948,"path":"/process-matched/Processed-product--1638680769938.csv","name":"shusmita","sheet":"09","business":[],"brand":[],"product_count":246},{"createdAt":1638705376140,"path":"/process-matched/Processed-product--1638705376133.csv","name":"Shusmita","sheet":"10","business":[],"brand":[],"product_count":147},{"createdAt":1638791866545,"path":"/process-matched/Processed-product--1638791866537.csv","name":"shusmita","sheet":"11","product_count":147,"business":[{"name":"squaretoiletrieslimited","count":147}],"brand":[{"name":"meril","count":36},{"name":"revive","count":10},{"name":"jui","count":9},{"name":"chaka","count":10},{"name":"kool","count":16},{"name":"fresh","count":3},{"name":"magic","count":3},{"name":"white-plus-kids","count":4},{"name":"sepnil","count":12},{"name":"zerocal","count":4},{"name":"spring","count":8},{"name":"xpel","count":2},{"name":"maxclean","count":4},{"name":"shakti","count":2},{"name":"un-categorized","count":2},{"name":"senora","count":9},{"name":"supermom","count":13}]}]}]}]